[
  {
    "path": "posts/De små tingene/",
    "title": "De små tingene",
    "description": "Hvis jeg gjør det jeg kan på mitt kontor, og du på ditt så må vi vel alle bli fornøyde med samfunnet?",
    "author": [
      {
        "name": "Endre Grüner Ofstad",
        "url": {}
      }
    ],
    "date": "2020-11-10",
    "categories": [
      "Forvaltning",
      "Økosystem"
    ],
    "preview": "posts/De små tingene/_MG_5420.jpg",
    "last_modified": "2020-10-11T23:06:49+02:00",
    "input_file": "DeSmåTingene.utf8.md"
  },
  {
    "path": "posts/welcome/",
    "title": "Velkommen",
    "description": "Velkommen til bloggen!",
    "author": [
      {
        "name": "Endre Grüner Ofstad",
        "url": {}
      }
    ],
    "date": "2020-10-11",
    "categories": [],
    "preview": {},
    "last_modified": "2020-10-11T18:00:35+02:00",
    "input_file": {}
  }
]
